{"match": {"id": 51, "stage": "group", "group": "C", "matchday": "MD3", "home_team": "Scotland", "away_team": "Brazil", "venue": "Hard Rock Stadium", "city": "Miami", "kickoff": "2026-06-24T18:00:00-04:00", "neutral": true, "weather": "", "home_rest_days": 4, "away_rest_days": 4, "home_score": null, "away_score": null, "played": false}, "prediction": {"home": "Scotland", "away": "Brazil", "neutral": true, "p_home": 0.1948, "p_draw": 0.2042, "p_away": 0.601, "expected_goals": {"home": 0.89, "away": 1.97}, "top_scores": [{"score": "0-2", "prob": 0.1113}, {"score": "1-1", "prob": 0.1086}, {"score": "0-1", "prob": 0.1052}], "confidence": 57, "upset_probability": 0.1948, "market_used": true, "members": {"dc": [0.1549, 0.2276, 0.6175], "poisson": [0.2371, 0.244, 0.5189], "elo": [0.188, 0.1147, 0.6974], "market": [0.2024, 0.1197, 0.6779], "xgb": [0.1132, 0.2005, 0.6863]}, "explanation": "Brazil is favoured (60% to win) over Scotland, with a 20% chance of a draw. Brazil projects to create more (xG 2.0 vs 0.9). Scotland is closer to full strength; Brazil is carrying notable injuries/suspensions. Demanding match conditions add variance and modestly level the tie. The betting market agrees, pricing Brazil at 68% to win. Moderate confidence (57/100): reasonable agreement across models.", "condition": {"logit_shift": -0.0356, "home_cond": 0.4443, "away_cond": 0.4448, "home_momentum": 26.64, "away_momentum": 15.41, "home_manager_wr": 0.5, "away_manager_wr": 0.6}, "predicted_winner": "Brazil", "favored_team": "Brazil", "win_reasons": ["Rodrygo (FW) is fit and firing \u2014 in 8.5/10 form, 3 goals in his last 5, at 97% fitness.", "Brazil's attack (rating 1.8) projects to break down Scotland's back line (concedes ~1.3/game).", "The score model projects Brazil to create more (xG 2.0 vs 0.9)."]}, "key_players": {"Scotland": {"attacking": [{"name": "Che Adams", "position": "FW", "club": "Torino", "number": null, "goals": 0, "assists": 0, "xg": 0.0, "xa": 0.0, "impact": 80, "fitness": "fit", "photo_url": ""}, {"name": "Lyndon Dykes", "position": "FW", "club": "Charlton Athletic", "number": null, "goals": 0, "assists": 0, "xg": 0.0, "xa": 0.0, "impact": 80, "fitness": "fit", "photo_url": ""}, {"name": "George Hirst", "position": "FW", "club": "Ipswich Town", "number": null, "goals": 0, "assists": 0, "xg": 0.0, "xa": 0.0, "impact": 80, "fitness": "fit", "photo_url": ""}], "defensive": [{"name": "Grant Hanley", "position": "DF", "club": "Hibernian", "number": null, "goals": 0, "assists": 0, "xg": 0.0, "xa": 0.0, "impact": 75, "fitness": "fit", "photo_url": ""}, {"name": "Jack Hendry", "position": "DF", "club": "Al-Ettifaq", "number": null, "goals": 0, "assists": 0, "xg": 0.0, "xa": 0.0, "impact": 75, "fitness": "fit", "photo_url": ""}]}, "Brazil": {"attacking": [{"name": "Vin\u00edcius J\u00fanior", "position": "FW", "club": "Real Madrid", "goals": 8, "assists": 6, "xg": 7.0, "xa": 4.5, "impact": 92, "fitness": "fit", "photo_url": ""}, {"name": "Raphinha", "position": "FW", "club": "Barcelona", "goals": 7, "assists": 7, "xg": 6.0, "xa": 5.5, "impact": 88, "fitness": "fit", "photo_url": ""}, {"name": "Rodrygo", "position": "FW", "club": "Real Madrid", "goals": 6, "assists": 5, "xg": 5.2, "xa": 3.8, "impact": 86, "fitness": "fit", "photo_url": ""}], "defensive": [{"name": "Alisson", "position": "GK", "club": "Liverpool", "goals": 0, "assists": 0, "xg": 0.0, "xa": 0.0, "impact": 88, "fitness": "fit", "photo_url": ""}, {"name": "Marquinhos", "position": "DF", "club": "PSG", "goals": 1, "assists": 0, "xg": 0.6, "xa": 0.2, "impact": 84, "fitness": "fit", "photo_url": ""}]}}, "team_comparison": {"Scotland": {"code": "SCT", "name": "Scotland", "group": "C", "elo": 1807.6, "fifa_rank": 31, "flag_url": "https://flagcdn.com/96x72/gb-sct.png", "manager": "Steve Clarke", "manager_winrate": 0.5, "strength_index": 72.5}, "Brazil": {"code": "BR", "name": "Brazil", "group": "C", "elo": 2034.2, "fifa_rank": 4, "flag_url": "https://flagcdn.com/96x72/br.png", "manager": "Carlo Ancelotti", "manager_winrate": 0.6, "strength_index": 100}}, "tactical": {"attack": {"Scotland": 0.89, "Brazil": 1.97}, "strength_index": {"Scotland": 72.5, "Brazil": 100}, "edge": "Brazil", "summary": "Brazil holds the attacking edge; the lower-xG side must rely on defensive organisation and transitions."}, "injuries": {"Scotland": [], "Brazil": [{"name": "Vin\u00edcius J\u00fanior", "position": "FW", "club": "Real Madrid", "goals": 8, "assists": 6, "xg": 7.0, "xa": 4.5, "impact": 92, "fitness": "doubt", "photo_url": "", "news": "injury: Thigh tightness", "return_date": "2026-06-21"}]}, "availability": {"Scotland": 1.0, "Brazil": 0.928}, "conditions": {"weather": {"temp_c": 34.8, "humidity": 57, "altitude_m": 2, "severity": 0.538, "summary": "demanding conditions \u2014 hot 35\u00b0C", "source": "live"}, "rest_days": {"Scotland": 4, "Brazil": 4}, "travel_km": {"Scotland": 1972.5, "Brazil": 1619.9}}}