{"match_id": 9, "home": "Germany", "away": "Cura\u00e7ao", "score": [7, 1], "generated": true, "scorers_source": "ESPN (web)", "maps_source": "model-generated", "disclaimer": "Goalscorers are real, collected from the web (ESPN). Shot map, heat map and passing network are model-generated illustrations \u2014 that coordinate-level data is not openly available (Sofascore/FotMob block automated access).", "scorers": {"home": [{"player": "Felix Nmecha", "minute": 6, "type": "goal"}, {"player": "Nico Schlotterbeck", "minute": 38, "type": "goal"}, {"player": "Jamal Musiala", "minute": 47, "type": "goal"}, {"player": "Kai Havertz", "minute": 50, "type": "penalty"}, {"player": "Nathaniel Brown", "minute": 68, "type": "goal"}, {"player": "Deniz Undav", "minute": 78, "type": "goal"}, {"player": "Kai Havertz", "minute": 88, "type": "goal"}], "away": [{"player": "Livano Comenencia", "minute": 21, "type": "goal"}]}, "post_match": {"headline": "Germany see off Cura\u00e7ao", "summary": "Germany swept aside Cura\u00e7ao 7-1. Kai Havertz struck 2 for the result.", "star_player": "Kai Havertz", "star_reason": "Scored 2 in the match.", "turning_point": null, "what_lacked": null, "sources": [], "auto": true}, "box_score": {"possession": [66, 34], "shots": [26, 14], "shots_on_target": [12, 5], "xg": [7.6, 0.9], "corners": [3, 2], "fouls": [9, 8], "yellow_cards": [3, 1]}, "shot_map": {"home": [{"x": 73.6, "y": 25.3, "xg": 0.6, "outcome": "goal", "player": "Kai Havertz"}, {"x": 67.1, "y": 17.0, "xg": 0.62, "outcome": "goal", "player": "Felix Nmecha"}, {"x": 67.2, "y": 23.4, "xg": 0.57, "outcome": "goal", "player": "Kai Havertz"}, {"x": 74.4, "y": 29.0, "xg": 0.33, "outcome": "goal", "player": "Leroy San\u00e9"}, {"x": 91.3, "y": 37.6, "xg": 0.31, "outcome": "goal", "player": "Kai Havertz"}, {"x": 64.2, "y": 18.9, "xg": 0.67, "outcome": "goal", "player": "Florian Wirtz"}, {"x": 88.7, "y": 29.3, "xg": 0.38, "outcome": "goal", "player": "Kai Havertz"}, {"x": 78.3, "y": 51.0, "xg": 0.27, "outcome": "on_target", "player": "Leroy San\u00e9"}, {"x": 51.3, "y": 34.2, "xg": 0.15, "outcome": "on_target", "player": "Nick Woltemade"}, {"x": 81.4, "y": 46.0, "xg": 0.09, "outcome": "on_target", "player": "Kai Havertz"}, {"x": 93.6, "y": 20.1, "xg": 0.02, "outcome": "off_target", "player": "Florian Wirtz"}, {"x": 96.0, "y": 30.1, "xg": 0.21, "outcome": "off_target", "player": "Nick Woltemade"}, {"x": 89.2, "y": 22.8, "xg": 0.02, "outcome": "on_target", "player": "Leroy San\u00e9"}, {"x": 61.9, "y": 32.7, "xg": 0.04, "outcome": "off_target", "player": "Joshua Kimmich"}, {"x": 76.3, "y": 40.7, "xg": 0.23, "outcome": "off_target", "player": "Nick Woltemade"}, {"x": 56.4, "y": 42.7, "xg": 0.26, "outcome": "on_target", "player": "Nick Woltemade"}, {"x": 52.3, "y": 17.9, "xg": 0.27, "outcome": "off_target", "player": "Jonathan Tah"}, {"x": 53.5, "y": 42.2, "xg": 0.08, "outcome": "blocked", "player": "Kai Havertz"}, {"x": 92.2, "y": 38.0, "xg": 0.26, "outcome": "off_target", "player": "Joshua Kimmich"}, {"x": 72.4, "y": 46.5, "xg": 0.05, "outcome": "off_target", "player": "Nick Woltemade"}, {"x": 85.7, "y": 26.2, "xg": 0.1, "outcome": "blocked", "player": "Joshua Kimmich"}, {"x": 77.9, "y": 34.6, "xg": 0.07, "outcome": "off_target", "player": "Kai Havertz"}, {"x": 84.1, "y": 10.6, "xg": 0.29, "outcome": "on_target", "player": "Leroy San\u00e9"}, {"x": 67.6, "y": 26.8, "xg": 0.12, "outcome": "off_target", "player": "Antonio R\u00fcdiger"}, {"x": 89.9, "y": 49.4, "xg": 0.24, "outcome": "on_target", "player": "Leroy San\u00e9"}, {"x": 69.7, "y": 12.8, "xg": 0.29, "outcome": "off_target", "player": "Joshua Kimmich"}], "away": [{"x": 21.7, "y": 35.0, "xg": 0.64, "outcome": "goal", "player": "Cura\u00e7ao Player 2"}, {"x": 29.6, "y": 26.1, "xg": 0.17, "outcome": "off_target", "player": "Cura\u00e7ao Player 1"}, {"x": 36.6, "y": 29.6, "xg": 0.11, "outcome": "on_target", "player": "Cura\u00e7ao #11"}, {"x": 15.7, "y": 15.8, "xg": 0.17, "outcome": "blocked", "player": "Cura\u00e7ao Player 1"}, {"x": 45.7, "y": 30.5, "xg": 0.28, "outcome": "blocked", "player": "Cura\u00e7ao #8"}, {"x": 4.1, "y": 50.4, "xg": 0.13, "outcome": "off_target", "player": "Cura\u00e7ao Player 3"}, {"x": 36.2, "y": 21.8, "xg": 0.12, "outcome": "off_target", "player": "Cura\u00e7ao Player 2"}, {"x": 10.6, "y": 33.2, "xg": 0.21, "outcome": "off_target", "player": "Cura\u00e7ao Player 2"}, {"x": 13.4, "y": 34.4, "xg": 0.17, "outcome": "on_target", "player": "Cura\u00e7ao Player 1"}, {"x": 10.1, "y": 31.6, "xg": 0.24, "outcome": "on_target", "player": "Cura\u00e7ao Player 1"}, {"x": 15.5, "y": 46.8, "xg": 0.05, "outcome": "on_target", "player": "Cura\u00e7ao Player 5"}, {"x": 12.2, "y": 41.7, "xg": 0.17, "outcome": "on_target", "player": "Cura\u00e7ao #11"}, {"x": 13.7, "y": 9.5, "xg": 0.16, "outcome": "on_target", "player": "Cura\u00e7ao Player 3"}, {"x": 35.4, "y": 20.6, "xg": 0.16, "outcome": "off_target", "player": "Cura\u00e7ao #8"}]}, "heat_map": {"home": [[0.15, 0.29, 0.44, 0.48, 0.48, 0.58], [0.22, 0.4, 0.55, 0.73, 0.76, 1.0], [0.23, 0.41, 0.5, 0.58, 0.83, 0.99], [0.23, 0.18, 0.35, 0.38, 0.53, 0.64]], "away": [[0.63, 0.57, 0.47, 0.39, 0.38, 0.21], [0.95, 0.73, 0.65, 0.57, 0.46, 0.38], [1.0, 0.97, 0.68, 0.58, 0.54, 0.29], [0.64, 0.61, 0.54, 0.33, 0.2, 0.3]]}, "passing_network": {"home": {"nodes": [{"player": "Manuel Neuer", "pos": "GK", "x": 6.0, "y": 32.0, "passes": 35}, {"player": "Antonio R\u00fcdiger", "pos": "DF", "x": 22.0, "y": 11.5, "passes": 31}, {"player": "Jonathan Tah", "pos": "DF", "x": 22.0, "y": 25.6, "passes": 47}, {"player": "David Raum", "pos": "DF", "x": 22.0, "y": 38.4, "passes": 55}, {"player": "Nico Schlotterbeck", "pos": "DF", "x": 22.0, "y": 52.5, "passes": 24}, {"player": "Joshua Kimmich", "pos": "MF", "x": 45.0, "y": 17.9, "passes": 31}, {"player": "Felix Nmecha", "pos": "MF", "x": 45.0, "y": 32.0, "passes": 58}, {"player": "Florian Wirtz", "pos": "MF", "x": 45.0, "y": 46.1, "passes": 52}, {"player": "Kai Havertz", "pos": "FW", "x": 70.0, "y": 14.1, "passes": 46}, {"player": "Leroy San\u00e9", "pos": "FW", "x": 72.0, "y": 32.0, "passes": 40}, {"player": "Nick Woltemade", "pos": "FW", "x": 70.0, "y": 49.9, "passes": 27}], "edges": [{"from": 0, "to": 2, "weight": 13}, {"from": 0, "to": 3, "weight": 22}, {"from": 1, "to": 2, "weight": 16}, {"from": 2, "to": 3, "weight": 11}, {"from": 3, "to": 4, "weight": 11}, {"from": 4, "to": 7, "weight": 13}, {"from": 5, "to": 6, "weight": 10}, {"from": 5, "to": 1, "weight": 15}, {"from": 6, "to": 7, "weight": 13}, {"from": 6, "to": 2, "weight": 7}, {"from": 7, "to": 3, "weight": 11}, {"from": 8, "to": 9, "weight": 20}, {"from": 8, "to": 5, "weight": 6}, {"from": 8, "to": 6, "weight": 20}, {"from": 9, "to": 10, "weight": 12}, {"from": 9, "to": 6, "weight": 8}, {"from": 10, "to": 7, "weight": 15}]}, "away": {"nodes": [{"player": "Cura\u00e7ao Player 6", "pos": "GK", "x": 94.0, "y": 32.0, "passes": 37}, {"player": "Cura\u00e7ao Player 5", "pos": "DF", "x": 78.0, "y": 11.5, "passes": 60}, {"player": "Cura\u00e7ao Player 3", "pos": "DF", "x": 78.0, "y": 25.6, "passes": 51}, {"player": "Cura\u00e7ao Player 4", "pos": "DF", "x": 78.0, "y": 38.4, "passes": 39}, {"player": "Cura\u00e7ao Player 5", "pos": "DF", "x": 78.0, "y": 52.5, "passes": 21}, {"player": "Cura\u00e7ao Player 3", "pos": "MF", "x": 55.0, "y": 17.9, "passes": 24}, {"player": "Cura\u00e7ao Player 4", "pos": "MF", "x": 55.0, "y": 32.0, "passes": 39}, {"player": "Cura\u00e7ao #8", "pos": "MF", "x": 55.0, "y": 46.1, "passes": 58}, {"player": "Cura\u00e7ao Player 1", "pos": "FW", "x": 30.0, "y": 14.1, "passes": 13}, {"player": "Cura\u00e7ao Player 2", "pos": "FW", "x": 28.0, "y": 32.0, "passes": 22}, {"player": "Cura\u00e7ao #11", "pos": "FW", "x": 30.0, "y": 49.9, "passes": 32}], "edges": [{"from": 0, "to": 2, "weight": 16}, {"from": 1, "to": 2, "weight": 22}, {"from": 1, "to": 5, "weight": 17}, {"from": 1, "to": 0, "weight": 21}, {"from": 2, "to": 3, "weight": 13}, {"from": 3, "to": 4, "weight": 8}, {"from": 4, "to": 7, "weight": 13}, {"from": 5, "to": 6, "weight": 7}, {"from": 6, "to": 7, "weight": 18}, {"from": 7, "to": 3, "weight": 18}, {"from": 8, "to": 9, "weight": 13}, {"from": 10, "to": 9, "weight": 9}, {"from": 10, "to": 7, "weight": 9}, {"from": 10, "to": 6, "weight": 14}]}}}