{"match": {"id": 9, "stage": "group", "group": "E", "matchday": "MD1", "home_team": "Germany", "away_team": "Cura\u00e7ao", "venue": "NRG Stadium", "city": "Houston", "kickoff": "2026-06-14T14:00:00-04:00", "neutral": true, "weather": "", "home_rest_days": 4, "away_rest_days": 4, "home_score": 7, "away_score": 1, "played": true}, "prediction": {"home": "Germany", "away": "Cura\u00e7ao", "neutral": true, "p_home": 0.9207, "p_draw": 0.0527, "p_away": 0.0266, "expected_goals": {"home": 5.28, "away": 0.57}, "total_goals": 5.84, "over_2_5": 0.9361, "top_scores": [{"score": "5-0", "prob": 0.1003}, {"score": "4-0", "prob": 0.0925}, {"score": "6-0", "prob": 0.0907}], "confidence": 99, "upset_probability": 0.0266, "market_used": true, "members": {"dc": [0.9741, 0.0202, 0.0057], "poisson": [0.6231, 0.1606, 0.2163], "elo": [0.8913, 0.0391, 0.0696], "market": [0.9018, 0.0344, 0.0638], "xgb": [0.746, 0.188, 0.066]}, "explanation": "Germany is favoured (92% to win) over Cura\u00e7ao, with a 5% chance of a draw. Germany projects to create more (xG 5.3 vs 0.6). Demanding match conditions add variance and modestly level the tie. The betting market agrees, pricing Germany at 90% to win. High confidence (99/100): models broadly agree.", "condition": {"logit_shift": 0.2337, "home_cond": 0.4934, "away_cond": 0.3934, "home_momentum": 4.88, "away_momentum": -4.88, "home_manager_wr": 0.6114, "away_manager_wr": 0.46, "home_gk_quality": 0.639, "away_gk_quality": 0.505, "home_db_coverage": 1.0, "away_db_coverage": 1.0, "player_scale": 1.0}, "predicted_winner": "Germany", "favored_team": "Germany", "win_reasons": ["Kai Havertz (FW) is fit and firing \u2014 in 10.0/10 form, 13 goals in his last 5, at 100% fitness.", "Germany carry WC2026 momentum (Elo +5 from results so far).", "Germany's attack (rating 3.5) projects to break down Cura\u00e7ao's back line (concedes ~1.3/game)."]}, "flow": {"engine": "match_flow_montecarlo", "n_sims": 6000, "mode": "group", "home_team": "Germany", "away_team": "Cura\u00e7ao", "winner": "Germany", "loser": "Cura\u00e7ao", "predicted_winner": "Germany", "win_probability": 0.9852, "predicted_score": "6-0", "shootout": false, "probabilities": {"home_win": 0.9852, "away_win": 0.0035, "regulation": {"home": 0.9852, "draw": 0.0113, "away": 0.0035}, "extra_time": 0.0, "shootout": 0.0, "shootout_winner": {"home": 0.5, "away": 0.5, "predicted": "Germany"}}, "expected_goals": {"home": 5.94, "away": 0.51}, "tournament_form": {"Germany": {"form_delta": -9.3, "played": 4, "w": 2, "d": 1, "l": 1, "gf": 11, "ga": 5, "record": "2W-1D-1L", "log": ["W 7-1 v Cura\u00e7ao", "W 2-1 v Ivory Coast", "L 1-2 v Ecuador", "D 1-1 v Paraguay"]}, "Cura\u00e7ao": {"form_delta": 2.3, "played": 3, "w": 0, "d": 1, "l": 2, "gf": 1, "ga": 9, "record": "0W-1D-2L", "log": ["L 1-7 v Germany", "D 0-0 v Ecuador", "L 0-2 v Ivory Coast"]}, "form_shift": -0.0986}, "most_likely_scores": [{"score": "6-0", "prob": 0.094}, {"score": "5-0", "prob": 0.094}, {"score": "7-0", "prob": 0.083}, {"score": "4-0", "prob": 0.082}], "scenarios": [{"key": "base", "label": "Base case", "score": "6-0", "xg": {"home": 5.9, "away": 0.5}, "likelihood": 0.094, "result": "regulation", "note": "The most likely flow \u2014 CAI's consensus across form, tactics and momentum."}, {"key": "upside", "label": "Upside \u00b7 Germany click", "score": "7-0", "xg": {"home": 7.4, "away": 0.4}, "likelihood": 0.083, "result": "regulation", "note": "Germany's current form holds and they convert their chances \u2014 the tie opens up and they pull clear."}, {"key": "downside", "label": "Downside \u00b7 Cura\u00e7ao frustrates", "score": "4-0", "xg": {"home": 3.0, "away": 3.0}, "likelihood": 0.082, "result": "regulation", "note": "A flat, low-margin night \u2014 Cura\u00e7ao sit in and the tie tightens."}], "pain_points": {"Germany": ["Cold run into the tie (2W-1D-1L, -9 Elo) \u2014 momentum is against them."], "Cura\u00e7ao": ["Goalkeeping is a soft spot under sustained pressure.", "Blunter in the final third \u2014 fewer clear chances created."]}, "match_flow": [{"minute": 13, "team": "Germany", "type": "goal", "text": "Kai Havertz strikes for Germany"}, {"minute": 27, "team": "Germany", "type": "goal", "text": "Kai Havertz strikes for Germany"}, {"minute": 42, "team": "Germany", "type": "goal", "text": "Kai Havertz strikes for Germany"}, {"minute": 45, "team": "Germany", "type": "goal", "text": "Kai Havertz strikes for Germany"}, {"minute": 48, "team": "Germany", "type": "goal", "text": "Kai Havertz strikes for Germany"}, {"minute": 61, "team": "Germany", "type": "goal", "text": "Kai Havertz strikes for Germany"}, {"minute": 64, "team": null, "type": "tactical", "text": "Attacking substitutions as both benches go for it"}], "turning_points": ["Kai Havertz strikes for Germany", "Kai Havertz strikes for Germany", "Kai Havertz strikes for Germany", "Kai Havertz strikes for Germany", "Kai Havertz strikes for Germany"], "key_players": {"Germany": {"likely_scorer": "Kai Havertz", "penalty_decider": "Kai Havertz", "watch": ["Kai Havertz", "Deniz Undav", "Felix Nmecha"]}, "Cura\u00e7ao": {"likely_scorer": "Livano Comenencia", "penalty_decider": "Livano Comenencia", "watch": ["Livano Comenencia", "Armando Obispo", "Deveron Fonville"]}}, "risk_factors": ["Cura\u00e7ao's goalkeeping is a relative weak point under pressure."], "explainability": {"model_weights": {"statistical_elo": 0.4, "player_form": 0.25, "tactical_matchup": 0.15, "weather_location": 0.1, "psychology_penalty": 0.1}, "reasons": ["Germany carries the sharper attack (3.50 vs 0.80 xG/match).", "Germany grades higher on form & big-match composure (42% vs 22%).", "Edge from the spot: Germany convert ~78% vs Cura\u00e7ao ~73% \u2014 decisive if it goes to pens.", "Current form favours Germany \u2014 group record 2W-1D-1L (-9 Elo) vs Cura\u00e7ao 0W-1D-2L (+2)."], "why_penalties": "Germany are favoured to take all three points (99%).", "what_could_change": "An early goal swings momentum; an injury to Germany's key creator, or Cura\u00e7ao stealing a set-piece, flips it.", "confidence": 99}, "confidence": 99}, "key_players": {"Germany": {"attacking": [{"name": "Kai Havertz", "position": "FW", "club": "Arsenal", "number": null, "goals": 3, "assists": 0, "xg": 0.0, "xa": 0.0, "impact": 81, "fitness": "fit", "photo_url": "https://upload.wikimedia.org/wikipedia/commons/thumb/7/74/1_kai_havertz_2026_%28cropped%29.jpg/330px-1_kai_havertz_2026_%28cropped%29.jpg"}, {"name": "Deniz Undav", "position": "FW", "club": "VfB Stuttgart", "number": null, "goals": 3, "assists": 0, "xg": 0.0, "xa": 0.0, "impact": 80, "fitness": "fit", "photo_url": "https://upload.wikimedia.org/wikipedia/commons/thumb/a/a5/Deniz_undav.jpg/330px-Deniz_undav.jpg"}, {"name": "Leroy San\u00e9", "position": "FW", "club": "Galatasaray", "number": null, "goals": 1, "assists": 0, "xg": 0.0, "xa": 0.0, "impact": 80, "fitness": "fit", "photo_url": "https://upload.wikimedia.org/wikipedia/commons/thumb/b/bf/FC_Red_Bull_Salzburg_gegen_Bayern_M%C3%BCnchen_%282025-01-06_Testspiel%29_22.jpg/330px-FC_Red_Bull_Salzburg_gegen_Bayern_M%C3%BCnchen_%282025-01-06_Testspiel%29_22.jpg"}], "defensive": [{"name": "Antonio R\u00fcdiger", "position": "DF", "club": "Real Madrid", "number": null, "goals": 0, "assists": 0, "xg": 0.0, "xa": 0.0, "impact": 75, "fitness": "fit", "photo_url": ""}, {"name": "Jonathan Tah", "position": "DF", "club": "Bayern Munich", "number": null, "goals": 0, "assists": 0, "xg": 0.0, "xa": 0.0, "impact": 75, "fitness": "fit", "photo_url": "https://upload.wikimedia.org/wikipedia/commons/thumb/0/0f/Jonathan_Tah_2019.jpg/330px-Jonathan_Tah_2019.jpg"}]}, "Cura\u00e7ao": {"attacking": [{"name": "Cura\u00e7ao Player 1", "position": "FW", "club": "\u2014", "goals": 0, "assists": 0, "xg": 0.0, "xa": 0.0, "impact": 70, "fitness": "fit", "photo_url": ""}, {"name": "Cura\u00e7ao Player 2", "position": "FW", "club": "\u2014", "goals": 0, "assists": 0, "xg": 0.0, "xa": 0.0, "impact": 67, "fitness": "fit", "photo_url": ""}, {"name": "Cura\u00e7ao Player 3", "position": "MF", "club": "\u2014", "goals": 0, "assists": 0, "xg": 0.0, "xa": 0.0, "impact": 64, "fitness": "fit", "photo_url": ""}], "defensive": [{"name": "Cura\u00e7ao Player 5", "position": "DF", "club": "\u2014", "goals": 0, "assists": 0, "xg": 0.0, "xa": 0.0, "impact": 58, "fitness": "fit", "photo_url": ""}, {"name": "Cura\u00e7ao Player 6", "position": "GK", "club": "\u2014", "goals": 0, "assists": 0, "xg": 0.0, "xa": 0.0, "impact": 55, "fitness": "fit", "photo_url": ""}]}}, "team_comparison": {"Germany": {"code": "DE", "name": "Germany", "group": "E", "elo": 2025.1, "fifa_rank": 6, "flag_url": "https://flagcdn.com/96x72/de.png", "manager": "Julian Nagelsmann", "manager_winrate": 0.61, "strength_index": 100}, "Cura\u00e7ao": {"code": "CW", "name": "Cura\u00e7ao", "group": "E", "elo": 1570.5, "fifa_rank": 47, "flag_url": "https://flagcdn.com/96x72/cw.png", "manager": "Dick Advocaat", "manager_winrate": 0.52, "strength_index": 38.6}}, "tactical": {"attack": {"Germany": 5.28, "Cura\u00e7ao": 0.57}, "strength_index": {"Germany": 100, "Cura\u00e7ao": 38.6}, "edge": "Germany", "summary": "Germany holds the attacking edge; the lower-xG side must rely on defensive organisation and transitions."}, "injuries": {"Germany": [{"name": "Leroy San\u00e9", "position": "FW", "club": "Galatasaray", "number": null, "goals": 1, "assists": 0, "xg": 0.0, "xa": 0.0, "impact": 80, "fitness": "out", "photo_url": "https://upload.wikimedia.org/wikipedia/commons/thumb/b/bf/FC_Red_Bull_Salzburg_gegen_Bayern_M%C3%BCnchen_%282025-01-06_Testspiel%29_22.jpg/330px-FC_Red_Bull_Salzburg_gegen_Bayern_M%C3%BCnchen_%282025-01-06_Testspiel%29_22.jpg", "news": "injury: Knee ligament", "return_date": "2026-06-28"}], "Cura\u00e7ao": []}, "availability": {"Germany": 0.9595, "Cura\u00e7ao": 1.0}, "conditions": {"weather": {"temp_c": 33, "humidity": 74, "altitude_m": 15, "severity": 0.474, "summary": "demanding conditions \u2014 hot 33\u00b0C, humid", "source": "climatology"}, "rest_days": {"Germany": 4, "Cura\u00e7ao": 4}, "travel_km": {"Germany": 0.0, "Cura\u00e7ao": 0.0}}}