{"match": {"id": 5, "stage": "group", "group": "C", "matchday": "MD1", "home_team": "Haiti", "away_team": "Scotland", "venue": "Gillette Stadium", "city": "Boston", "kickoff": "2026-06-13T21:00:00-04:00", "neutral": true, "weather": "", "home_rest_days": 4, "away_rest_days": 4, "home_score": 0, "away_score": 1, "played": true}, "prediction": {"home": "Haiti", "away": "Scotland", "neutral": true, "p_home": 0.1761, "p_draw": 0.1969, "p_away": 0.6269, "expected_goals": {"home": 0.76, "away": 1.94}, "top_scores": [{"score": "0-2", "prob": 0.126}, {"score": "0-1", "prob": 0.1217}, {"score": "1-1", "prob": 0.1069}], "confidence": 59, "upset_probability": 0.1761, "market_used": true, "members": {"dc": [0.131, 0.2248, 0.6442], "poisson": [0.2612, 0.2489, 0.4899], "elo": [0.2291, 0.1446, 0.6263], "market": [0.2374, 0.1441, 0.6186], "xgb": [0.1888, 0.2759, 0.5353]}, "explanation": "Scotland is favoured (63% to win) over Haiti, with a 20% chance of a draw. Scotland projects to create more (xG 1.9 vs 0.8). The betting market agrees, pricing Scotland at 62% to win. Moderate confidence (59/100): reasonable agreement across models.", "condition": {"logit_shift": -0.0703, "home_cond": 0.3986, "away_cond": 0.4443, "home_momentum": -26.64, "away_momentum": 26.64, "home_manager_wr": 0.45, "away_manager_wr": 0.5}, "predicted_winner": "Scotland", "favored_team": "Scotland", "win_reasons": ["John McGinn (CM) is fit and firing \u2014 in 9.5/10 form, 6 goals in his last 5, at 97% fitness.", "Scotland carry WC2026 momentum (Elo +27 from results so far).", "The score model projects Scotland to create more (xG 1.9 vs 0.8)."]}, "key_players": {"Haiti": {"attacking": [{"name": "Dominique Simon", "position": "FW", "club": "Tatran Presov", "number": null, "goals": 0, "assists": 0, "xg": 0.0, "xa": 0.0, "impact": 81, "fitness": "fit", "photo_url": ""}, {"name": "Duckens Nazon", "position": "FW", "club": "Esteghlal", "number": null, "goals": 0, "assists": 0, "xg": 0.0, "xa": 0.0, "impact": 81, "fitness": "fit", "photo_url": ""}, {"name": "Frantzdy Pierrot", "position": "FW", "club": "Caykur Rizespor", "number": null, "goals": 0, "assists": 0, "xg": 0.0, "xa": 0.0, "impact": 81, "fitness": "fit", "photo_url": ""}], "defensive": [{"name": "Ricardo Ade", "position": "DF", "club": "LDU Quito", "number": null, "goals": 0, "assists": 0, "xg": 0.0, "xa": 0.0, "impact": 75, "fitness": "fit", "photo_url": ""}, {"name": "Carlens Arcus", "position": "DF", "club": "Angers", "number": null, "goals": 0, "assists": 0, "xg": 0.0, "xa": 0.0, "impact": 75, "fitness": "fit", "photo_url": ""}]}, "Scotland": {"attacking": [{"name": "Che Adams", "position": "FW", "club": "Torino", "number": null, "goals": 0, "assists": 0, "xg": 0.0, "xa": 0.0, "impact": 80, "fitness": "fit", "photo_url": ""}, {"name": "Lyndon Dykes", "position": "FW", "club": "Charlton Athletic", "number": null, "goals": 0, "assists": 0, "xg": 0.0, "xa": 0.0, "impact": 80, "fitness": "fit", "photo_url": ""}, {"name": "George Hirst", "position": "FW", "club": "Ipswich Town", "number": null, "goals": 0, "assists": 0, "xg": 0.0, "xa": 0.0, "impact": 80, "fitness": "fit", "photo_url": ""}], "defensive": [{"name": "Grant Hanley", "position": "DF", "club": "Hibernian", "number": null, "goals": 0, "assists": 0, "xg": 0.0, "xa": 0.0, "impact": 75, "fitness": "fit", "photo_url": ""}, {"name": "Jack Hendry", "position": "DF", "club": "Al-Ettifaq", "number": null, "goals": 0, "assists": 0, "xg": 0.0, "xa": 0.0, "impact": 75, "fitness": "fit", "photo_url": ""}]}}, "team_comparison": {"Haiti": {"code": "HT", "name": "Haiti", "group": "C", "elo": 1647.6, "fifa_rank": 45, "flag_url": "https://flagcdn.com/96x72/ht.png", "manager": "S\u00e9bastien Mign\u00e9", "manager_winrate": 0.45, "strength_index": 49.7}, "Scotland": {"code": "SCT", "name": "Scotland", "group": "C", "elo": 1807.6, "fifa_rank": 31, "flag_url": "https://flagcdn.com/96x72/gb-sct.png", "manager": "Steve Clarke", "manager_winrate": 0.5, "strength_index": 72.5}}, "tactical": {"attack": {"Haiti": 0.76, "Scotland": 1.94}, "strength_index": {"Haiti": 49.7, "Scotland": 72.5}, "edge": "Scotland", "summary": "Scotland holds the attacking edge; the lower-xG side must rely on defensive organisation and transitions."}, "injuries": {"Haiti": [], "Scotland": []}, "availability": {"Haiti": 1.0, "Scotland": 1.0}, "conditions": {"weather": {"temp_c": 24, "humidity": 64, "altitude_m": 45, "severity": 0.0, "summary": "mild 24\u00b0C", "source": "climatology"}, "rest_days": {"Haiti": 4, "Scotland": 4}, "travel_km": {"Haiti": 0.0, "Scotland": 0.0}}}