{"featured_matches": [{"id": 55, "stage": "group", "group": "E", "matchday": "MD3", "home_team": "Ecuador", "away_team": "Germany", "venue": "MetLife Stadium", "city": "New York/NJ", "kickoff": "2026-06-25T16:00:00-04:00", "neutral": true, "weather": "", "home_rest_days": 4, "away_rest_days": 4, "home_score": null, "away_score": null, "played": false, "home_flag": "https://flagcdn.com/96x72/ec.png", "away_flag": "https://flagcdn.com/96x72/de.png", "p_home": 0.2852, "p_draw": 0.2206, "p_away": 0.4942, "confidence": 26, "top_score": {"score": "1-1", "prob": 0.1439}, "top_scores": [{"score": "1-1", "prob": 0.1439}, {"score": "0-0", "prob": 0.1385}, {"score": "0-1", "prob": 0.1374}], "predicted_winner": "Germany", "expected_goals": {"home": 0.9, "away": 1.16}, "total_goals": 2.06, "over_2_5": 0.3394, "upset_probability": 0.2852, "market_used": true}, {"id": 56, "stage": "group", "group": "E", "matchday": "MD3", "home_team": "Cura\u00e7ao", "away_team": "Ivory Coast", "venue": "Lincoln Financial Field", "city": "Philadelphia", "kickoff": "2026-06-25T16:00:00-04:00", "neutral": true, "weather": "", "home_rest_days": 4, "away_rest_days": 4, "home_score": null, "away_score": null, "played": false, "home_flag": "https://flagcdn.com/96x72/cw.png", "away_flag": "https://flagcdn.com/96x72/ci.png", "p_home": 0.1182, "p_draw": 0.1094, "p_away": 0.7724, "confidence": 61, "top_score": {"score": "0-2", "prob": 0.1575}, "top_scores": [{"score": "0-2", "prob": 0.1575}, {"score": "0-3", "prob": 0.1317}, {"score": "0-1", "prob": 0.1206}], "predicted_winner": "Ivory Coast", "expected_goals": {"home": 0.49, "away": 2.51}, "total_goals": 2.99, "over_2_5": 0.5752, "upset_probability": 0.1182, "market_used": true}, {"id": 57, "stage": "group", "group": "F", "matchday": "MD3", "home_team": "Japan", "away_team": "Sweden", "venue": "AT&T Stadium", "city": "Dallas", "kickoff": "2026-06-25T19:00:00-04:00", "neutral": true, "weather": "", "home_rest_days": 4, "away_rest_days": 4, "home_score": null, "away_score": null, "played": false, "home_flag": "https://flagcdn.com/96x72/jp.png", "away_flag": "https://flagcdn.com/96x72/se.png", "p_home": 0.5937, "p_draw": 0.1774, "p_away": 0.2289, "confidence": 32, "top_score": {"score": "2-1", "prob": 0.0931}, "top_scores": [{"score": "2-1", "prob": 0.0931}, {"score": "2-0", "prob": 0.0875}, {"score": "3-1", "prob": 0.0793}], "predicted_winner": "Japan", "expected_goals": {"home": 2.55, "away": 1.07}, "total_goals": 3.62, "over_2_5": 0.7004, "upset_probability": 0.2289, "market_used": true}, {"id": 58, "stage": "group", "group": "F", "matchday": "MD3", "home_team": "Tunisia", "away_team": "Netherlands", "venue": "Arrowhead Stadium", "city": "Kansas City", "kickoff": "2026-06-25T19:00:00-04:00", "neutral": true, "weather": "", "home_rest_days": 4, "away_rest_days": 4, "home_score": null, "away_score": null, "played": false, "home_flag": "https://flagcdn.com/96x72/tn.png", "away_flag": "https://flagcdn.com/96x72/nl.png", "p_home": 0.1459, "p_draw": 0.115, "p_away": 0.7391, "confidence": 55, "top_score": {"score": "0-2", "prob": 0.109}, "top_scores": [{"score": "0-2", "prob": 0.109}, {"score": "0-3", "prob": 0.1066}, {"score": "1-2", "prob": 0.0809}], "predicted_winner": "Netherlands", "expected_goals": {"home": 0.74, "away": 2.93}, "total_goals": 3.67, "over_2_5": 0.7104, "upset_probability": 0.1459, "market_used": true}, {"id": 59, "stage": "group", "group": "D", "matchday": "MD3", "home_team": "Turkey", "away_team": "United States", "venue": "SoFi Stadium", "city": "Los Angeles", "kickoff": "2026-06-25T22:00:00-04:00", "neutral": true, "weather": "", "home_rest_days": 4, "away_rest_days": 4, "home_score": null, "away_score": null, "played": false, "home_flag": "https://flagcdn.com/96x72/tr.png", "away_flag": "https://flagcdn.com/96x72/us.png", "p_home": 0.3035, "p_draw": 0.2192, "p_away": 0.4773, "confidence": 32, "top_score": {"score": "1-1", "prob": 0.1005}, "top_scores": [{"score": "1-1", "prob": 0.1005}, {"score": "2-1", "prob": 0.088}, {"score": "1-2", "prob": 0.0732}], "predicted_winner": "United States", "expected_goals": {"home": 1.89, "away": 1.58}, "total_goals": 3.47, "over_2_5": 0.6736, "upset_probability": 0.3035, "market_used": true}, {"id": 60, "stage": "group", "group": "D", "matchday": "MD3", "home_team": "Paraguay", "away_team": "Australia", "venue": "Levi's Stadium", "city": "San Francisco", "kickoff": "2026-06-25T22:00:00-04:00", "neutral": true, "weather": "", "home_rest_days": 4, "away_rest_days": 4, "home_score": null, "away_score": null, "played": false, "home_flag": "https://flagcdn.com/96x72/py.png", "away_flag": "https://flagcdn.com/96x72/au.png", "p_home": 0.3141, "p_draw": 0.2495, "p_away": 0.4365, "confidence": 26, "top_score": {"score": "0-0", "prob": 0.1477}, "top_scores": [{"score": "0-0", "prob": 0.1477}, {"score": "1-1", "prob": 0.1464}, {"score": "0-1", "prob": 0.1285}], "predicted_winner": "Australia", "expected_goals": {"home": 0.97, "away": 1.02}, "total_goals": 1.99, "over_2_5": 0.321, "upset_probability": 0.4365, "market_used": true}], "top_winners": [{"team": "Argentina", "title_prob": 0.27}, {"team": "Spain", "title_prob": 0.104}, {"team": "England", "title_prob": 0.085}, {"team": "France", "title_prob": 0.07}, {"team": "Brazil", "title_prob": 0.063}, {"team": "Germany", "title_prob": 0.062}, {"team": "Morocco", "title_prob": 0.049}, {"team": "Colombia", "title_prob": 0.045}, {"team": "Japan", "title_prob": 0.045}, {"team": "Portugal", "title_prob": 0.034}], "title_chart": [{"team": "Argentina", "Champion": 0.27, "Final": 0.369, "SF": 0.495}, {"team": "Spain", "Champion": 0.104, "Final": 0.189, "SF": 0.313}, {"team": "England", "Champion": 0.085, "Final": 0.159, "SF": 0.276}, {"team": "France", "Champion": 0.07, "Final": 0.14, "SF": 0.257}, {"team": "Brazil", "Champion": 0.063, "Final": 0.129, "SF": 0.242}, {"team": "Germany", "Champion": 0.062, "Final": 0.13, "SF": 0.246}, {"team": "Morocco", "Champion": 0.049, "Final": 0.101, "SF": 0.197}, {"team": "Colombia", "Champion": 0.045, "Final": 0.099, "SF": 0.198}, {"team": "Japan", "Champion": 0.045, "Final": 0.098, "SF": 0.195}, {"team": "Portugal", "Champion": 0.034, "Final": 0.079, "SF": 0.169}], "dark_horses": [{"team": "Switzerland", "elo_rank": 18, "semi_prob": 0.105, "title_prob": 0.014, "note": "Seeded #18 but reaches the semis in 10% of simulations \u2014 a live dark horse."}, {"team": "Morocco", "elo_rank": 11, "semi_prob": 0.197, "title_prob": 0.049, "note": "Seeded #11 but reaches the semis in 20% of simulations \u2014 a live dark horse."}, {"team": "Japan", "elo_rank": 10, "semi_prob": 0.195, "title_prob": 0.045, "note": "Seeded #10 but reaches the semis in 20% of simulations \u2014 a live dark horse."}, {"team": "Norway", "elo_rank": 13, "semi_prob": 0.157, "title_prob": 0.029, "note": "Seeded #13 but reaches the semis in 16% of simulations \u2014 a live dark horse."}], "model_update": {"started": "2026-06-22T15:53:16.377270+00:00", "n_matches": 49445, "latest_match": "2026-06-21", "ingest": {"ok": true, "secs": 0.7}, "n_players": 1215, "players": {"ok": true, "secs": 0.0}, "elo": {"ok": true, "secs": 0.3}, "dixon_coles": {"ok": true, "secs": 300.1}, "xgboost": {"ok": true, "secs": 3.4}, "neural_net": {"ok": true, "secs": 5.2}, "simulate": {"ok": true, "secs": 68.8}, "calibration": [{"model": "dixon_coles", "n": 192, "RPS": 0.205, "LogLoss": 0.984, "Acc": 0.5417}, {"model": "elo", "n": 192, "RPS": 0.2065, "LogLoss": 0.9915, "Acc": 0.5521}, {"model": "base_rate", "n": 192, "RPS": 0.2427, "LogLoss": 1.0759, "Acc": 0.4271}, {"model": "uniform", "n": 192, "RPS": 0.2422, "LogLoss": 1.0986, "Acc": 0.4271}], "calibrate": {"ok": true, "secs": 476.2}, "finished": "2026-06-22T16:07:31.215960+00:00"}}