{"code": "ES", "name": "Spain", "group": "H", "elo": 2126.9, "fifa_rank": 2, "flag_url": "https://flagcdn.com/96x72/es.png", "manager": "Luis de la Fuente", "manager_winrate": 0.7, "strength_index": 100, "squad": [{"name": "Lamine Yamal", "position": "FW", "club": "Barcelona", "goals": 1, "assists": 0, "xg": 5.5, "xa": 6.8, "impact": 92, "fitness": "fit", "photo_url": ""}, {"name": "Nico Williams", "position": "FW", "club": "Athletic Club", "goals": 0, "assists": 0, "xg": 4.6, "xa": 4.0, "impact": 87, "fitness": "fit", "photo_url": "https://upload.wikimedia.org/wikipedia/commons/thumb/1/1d/ATHLETIC-OSASUNA_SEMIFINAL._MAIDER_GOIKOETXEA_%28168%29_%28cropped%29.jpg/330px-ATHLETIC-OSASUNA_SEMIFINAL._MAIDER_GOIKOETXEA_%28168%29_%28cropped%29.jpg"}, {"name": "Rodri", "position": "MF", "club": "Man City", "goals": 0, "assists": 0, "xg": 1.8, "xa": 2.6, "impact": 90, "fitness": "fit", "photo_url": ""}, {"name": "Pedri", "position": "MF", "club": "Barcelona", "goals": 0, "assists": 0, "xg": 1.9, "xa": 3.8, "impact": 88, "fitness": "fit", "photo_url": "https://upload.wikimedia.org/wikipedia/commons/thumb/1/13/Pedri.jpg/330px-Pedri.jpg"}, {"name": "Robin Le Normand", "position": "DF", "club": "Atl\u00e9tico Madrid", "goals": 0, "assists": 0, "xg": 0.4, "xa": 0.2, "impact": 83, "fitness": "fit", "photo_url": ""}, {"name": "Unai Sim\u00f3n", "position": "GK", "club": "Athletic Club", "goals": 0, "assists": 0, "xg": 0.0, "xa": 0.0, "impact": 84, "fitness": "fit", "photo_url": "https://upload.wikimedia.org/wikipedia/commons/thumb/b/ba/Unai_Sim%C3%B3n_2025_%28cropped%29.jpg/330px-Unai_Sim%C3%B3n_2025_%28cropped%29.jpg"}], "key_players": {"attacking": [{"name": "Lamine Yamal", "position": "FW", "club": "Barcelona", "goals": 1, "assists": 0, "xg": 5.5, "xa": 6.8, "impact": 92, "fitness": "fit", "photo_url": ""}, {"name": "Rodri", "position": "MF", "club": "Man City", "goals": 0, "assists": 0, "xg": 1.8, "xa": 2.6, "impact": 90, "fitness": "fit", "photo_url": ""}, {"name": "Pedri", "position": "MF", "club": "Barcelona", "goals": 0, "assists": 0, "xg": 1.9, "xa": 3.8, "impact": 88, "fitness": "fit", "photo_url": "https://upload.wikimedia.org/wikipedia/commons/thumb/1/13/Pedri.jpg/330px-Pedri.jpg"}], "defensive": [{"name": "Unai Sim\u00f3n", "position": "GK", "club": "Athletic Club", "goals": 0, "assists": 0, "xg": 0.0, "xa": 0.0, "impact": 84, "fitness": "fit", "photo_url": "https://upload.wikimedia.org/wikipedia/commons/thumb/b/ba/Unai_Sim%C3%B3n_2025_%28cropped%29.jpg/330px-Unai_Sim%C3%B3n_2025_%28cropped%29.jpg"}, {"name": "Robin Le Normand", "position": "DF", "club": "Atl\u00e9tico Madrid", "goals": 0, "assists": 0, "xg": 0.4, "xa": 0.2, "impact": 83, "fitness": "fit", "photo_url": ""}]}, "availability": 1.0, "injury_report": [], "group_rivals": ["Cape Verde", "Saudi Arabia", "Uruguay"], "progression": {"advance_R32": 0.995, "reach_QF": 0.543, "reach_SF": 0.364, "reach_Final": 0.224, "win_title": 0.126}}